cppcpyutils/LT_db_extractor.py
cppcpyutils/__init__.py
cppcpyutils/compute.py
cppcpyutils/io.py
cppcpyutils/roi.py
cppcpyutils/utils.py
cppcpyutils/viz.py
cppcpyutils-0.3.6.dist-info/entry_points.txt
cppcpyutils-0.3.6.dist-info/LICENSE
cppcpyutils-0.3.6.dist-info/WHEEL
cppcpyutils-0.3.6.dist-info/METADATA
cppcpyutils-0.3.6.dist-info/RECORD
